odoo/addons/web_remember_tree_column_width/README.rst
odoo/addons/web_remember_tree_column_width/__init__.py
odoo/addons/web_remember_tree_column_width/__manifest__.py
odoo/addons/web_remember_tree_column_width/i18n/it.po
odoo/addons/web_remember_tree_column_width/i18n/web_remember_tree_column_width.pot
odoo/addons/web_remember_tree_column_width/readme/CONTRIBUTORS.md
odoo/addons/web_remember_tree_column_width/readme/DESCRIPTION.md
odoo/addons/web_remember_tree_column_width/static/description/icon.png
odoo/addons/web_remember_tree_column_width/static/description/index.html
odoo/addons/web_remember_tree_column_width/static/src/js/list_renderer.esm.js
odoo/addons/web_remember_tree_column_width/static/src/scss/main.scss
odoo_addon_web_remember_tree_column_width-19.0.1.0.0.2.dist-info/METADATA
odoo_addon_web_remember_tree_column_width-19.0.1.0.0.2.dist-info/WHEEL
odoo_addon_web_remember_tree_column_width-19.0.1.0.0.2.dist-info/top_level.txt
odoo_addon_web_remember_tree_column_width-19.0.1.0.0.2.dist-info/RECORD
