Metadata-Version: 2.1
Name: odoo-addon-web_remember_tree_column_width
Version: 19.0.1.0.0.2
Requires-Dist: odoo==19.0.*
Summary: Remember the tree columns' widths across sessions.
Home-page: https://github.com/OCA/web
License: LGPL-3
Author: Vauxoo, Odoo Community Association (OCA)
Author-email: support@odoo-community.org
Classifier: Programming Language :: Python
Classifier: Framework :: Odoo
Classifier: Framework :: Odoo :: 19.0
Classifier: License :: OSI Approved :: GNU Lesser General Public License v3 (LGPLv3)
